Workbook

Sheet Trade Log
A1: Trade # | B1: Entry Date | C1: Exit Date | D1: Symbol | E1: Action | F1: Shares | G1: Entry Price | H1: Exit Price | I1: Entry Value | J1: Exit Value | K1: Gross P&L | L1: Commission | M1: Net P&L | N1: Return %
A2: 1 | B2: 45981 | C2: 45985.512 | D2: BRK.B | E2: LONG | F2: 9 | G2: 501.26 | H2: 504.04 | I2: =F2*G2 | J2: =F2*H2 | K2: =J2-I2 | L2: 2 | M2: =K2-L2 | N2: =M2/I2
A3: 2 | B3: 45981 | C3: 45985.512 | D3: TLRY | E3: LONG | F3: 5201 | G3: 0.962 | H3: 0.9059 | I3: =F3*G3 | J3: =F3*H3 | K3: =J3-I3 | L3: 2 | M3: =K3-L3 | N3: =M3/I3
A4: 3 | B4: 45981 | C4: 45985.512 | D4: MMC | E4: LONG | F4: 28 | G4: 177.13 | H4: 180.92 | I4: =F4*G4 | J4: =F4*H4 | K4: =J4-I4 | L4: 2 | M4: =K4-L4 | N4: =M4/I4
A5: 4 | B5: 45981 | C5: 45985.687 | D5: UPST | E5: LONG | F5: 134 | G5: 37.27 | H5: 39.02 | I5: =F5*G5 | J5: =F5*H5 | K5: =J5-I5 | L5: 2 | M5: =K5-L5 | N5: =M5/I5
A6: 5 | B6: 45981 | C6: 45985.687 | D6: ACB | E6: LONG | F6: 1163 | G6: 4.3 | H6: 4.36 | I6: =F6*G6 | J6: =F6*H6 | K6: =J6-I6 | L6: 2 | M6: =K6-L6 | N6: =M6/I6
A7: 6 | B7: 45985 | C7: 45985.687 | D7: EMR | E7: LONG | F7: 39 | G7: 128.22 | H7: 128.62 | I7: =F7*G7 | J7: =F7*H7 | K7: =J7-I7 | L7: 2 | M7: =K7-L7 | N7: =M7/I7
A8: 7 | B8: 45985 | C8: 45985.687 | D8: MRNA | E8: LONG | F8: 210 | G8: 23.72 | H8: 24.15 | I8: =F8*G8 | J8: =F8*H8 | K8: =J8-I8 | L8: 2 | M8: =K8-L8 | N8: =M8/I8
A9: 8 | B9: 45981 | C9: 45985.687 | D9: TGT | E9: LONG | F9: 58 | G9: 86.08 | H9: 84.54 | I9: =F9*G9 | J9: =F9*H9 | K9: =J9-I9 | L9: 2 | M9: =K9-L9 | N9: =M9/I9
A10: 9 | B10: 45981 | C10: 45985.687 | D10: SPOT | E10: LONG | F10: 8 | G10: 618.53 | H10: 584.98 | I10: =F10*G10 | J10: =F10*H10 | K10: =J10-I10 | L10: 2 | M10: =K10-L10 | N10: =M10/I10
A11: 10 | B11: 45981 | C11: 45985.687 | D11: DASH | E11: LONG | F11: 24 | G11: 202.315 | H11: 188.08 | I11: =F11*G11 | J11: =F11*H11 | K11: =J11-I11 | L11: 2 | M11: =K11-L11 | N11: =M11/I11
A12: 11 | B12: 45981 | C12: 45986.71 | D12: SNDL | E12: LONG | F12: 3089 | G12: 1.62 | H12: 1.74 | I12: =F12*G12 | J12: =F12*H12 | K12: =J12-I12 | L12: 2 | M12: =K12-L12 | N12: =M12/I12
A13: 12 | B13: 45985 | C13: 45986.71 | D13: ARKG | E13: LONG | F13: 150 | G13: 30.39 | H13: 31.14 | I13: =F13*G13 | J13: =F13*H13 | K13: =J13-I13 | L13: 2 | M13: =K13-L13 | N13: =M13/I13
... A60: 59 | B60: 45987 | C60: 45989 | D60: AGG | E60: LONG | F60: 49 | G60: 100.76 | H60: 100.76 | I60: =F60*G60 | J60: =F60*H60 | K60: =J60-I60 | L60: 2 | M60: =K60-L60 | N60: =M60/I60
B61: 45989 | C61: 46006.549 | D61: MELI | E61: LONG | F61: 2 | G61: 2033.32 | H61: 2015.89 | I61: 4066.64 | J61: 4031.78 | K61: =J61-I61 | L61: 2 | M61: =K61-L61 | N61: =M61/I61 | O61: 17 | P61: =IF(M61>0,"Win","Loss") | Q61: VPVMA | R61: BULL | S61: Universe Drop
B62: 45989 | C62: 46006.549 | D62: TLT | E62: LONG | F62: 54 | G62: 90.64 | H62: 87.34 | I62: 4894.56 | J62: 4716.36 | K62: =J62-I62 | L62: 2 | M62: =K62-L62 | N62: =M62/I62 | O62: 17 | P62: =IF(M62>0,"Win","Loss") | Q62: VPVMA | R62: BULL | S62: Universe Drop
B63: 46006 | C63: 46007.528 | D63: INTC | E63: LONG | F63: 131 | G63: 37.81 | H63: 37.51 | I63: 4953.11 | J63: 4913.81 | K63: =J63-I63 | L63: 2 | M63: =K63-L63 | N63: =M63/I63 | O63: 1 | P63: =IF(M63>0,"Win","Loss") | Q63: VPVMA | R63: BULL | S63: Signal
B64: 46006 | C64: 46007.704 | D64: GE | E64: LONG | F64: 16 | G64: 299.81 | H64: 298.73 | I64: 4796.96 | J64: 4779.68 | K64: =J64-I64 | L64: 2 | M64: =K64-L64 | N64: =M64/I64 | O64: 1 | P64: =IF(M64>0,"Win","Loss") | Q64: VPVMA | R64: BULL | S64: Signal
B65: 46006 | C65: 46007.704 | D65: PG | E65: LONG | F65: 34 | G65: 142.84 | H65: 145.21 | I65: 4856.56 | J65: 4937.14 | K65: =J65-I65 | L65: 2 | M65: =K65-L65 | N65: =M65/I65 | O65: 1 | P65: =IF(M65>0,"Win","Loss") | Q65: VPVMA | R65: BULL | S65: Signal
B66: 46007 | C66: 46007.704 | D66: NOW | E66: LONG | F66: 6 | G66: 765.2 | H66: 781.12 | I66: 4591.2 | J66: 4686.72 | K66: =J66-I66 | L66: 2 | M66: =K66-L66 | N66: =M66/I66 | O66: 0 | P66: =IF(M66>0,"Win","Loss") | Q66: VPVMA | R66: BULL | S66: Signal
B67: 46006 | C67: 46009.417 | D67: KO | E67: LONG | F67: 70 | G67: 70.52 | H67: 70.67 | I67: 4936.4 | J67: 4946.9 | K67: =J67-I67 | L67: 2 | M67: =K67-L67 | N67: =M67/I67 | O67: 3 | P67: =IF(M67>0,"Win","Loss") | Q67: VPVMA | R67: BULL | S67: Signal
B68: 46006 | C68: 46013.42 | D68: META | E68: LONG | F68: 7 | G68: 644.23 | H68: 658.77 | I68: 4509.61 | J68: 4611.39 | K68: =J68-I68 | L68: 2 | M68: =K68-L68 | N68: =M68/I68 | O68: 7 | P68: =IF(M68>0,"Win","Loss") | Q68: VPVMA | R68: BULL | S68: Signal
B69: 46006 | C69: 46013.42 | D69: COST | E69: LONG | F69: 5 | G69: 884.47 | H69: 855.62 | I69: 4422.35 | J69: 4278.1 | K69: =J69-I69 | L69: 2 | M69: =K69-L69 | N69: =M69/I69 | O69: 7 | P69: =IF(M69>0,"Win","Loss") | Q69: VPVMA | R69: BULL | S69: Signal
B70: 46009 | C70: 46013.42 | D70: GE | E70: LONG | F70: 17 | G70: 292.18 | H70: 307.21 | I70: 4967.06 | J70: 5222.57 | K70: =J70-I70 | L70: 2 | M70: =K70-L70 | N70: =M70/I70 | O70: 4 | P70: =IF(M70>0,"Win","Loss") | Q70: VPVMA | R70: BULL | S70: Signal
B71: 46006 | C71: 46014.651 | D71: AVGO | E71: LONG | F71: 13 | G71: 359.93 | H71: 341.45 | I71: 4679.09 | J71: 4438.85 | K71: =J71-I71 | L71: 2 | M71: =K71-L71 | N71: =M71/I71 | O71: 8 | P71: =IF(M71>0,"Win","Loss") | Q71: VPVMA | R71: BULL | S71: Signal
B72: 46013 | C72: 46014.651 | D72: HD | E72: LONG | F72: 14 | G72: 345 | H72: 346.39 | I72: 4830 | J72: 4849.46 | K72: =J72-I72 | L72: 2 | M72: =K72-L72 | N72: =M72/I72 | O72: 1 | P72: =IF(M72>0,"Win","Loss") | Q72: VPVMA | R72: BULL | S72: Signal
... B118: 46063 | C118: 46134.647 | D118: NFLX | E118: LONG | F118: 65 | G118: 82.21 | H118: 92.58 | I118: 5343.65 | J118: 6017.7 | K118: =J118-I118 | L118: 2 | M118: =K118-L118 | N118: =M118/I118 | O118: 71 | P118: =IF(M118>0,"Win","Loss") | Q118: VPVMA | R118: BULL | S118: Universe Drop

Sheet Dashboard
A1: Portfolio Dashboard
A3: Initial Capital: | B3: 100000
A4: Total Realized P&L: | B4: =SUM('Trade Log'!M:M)
A5: Available Cash: | B5: 90568.98
A7: Trading Statistics
A8: Total Trades: | B8: =COUNTA('Trade Log'!D:D)-1
A9: Winning Trades: | B9: =COUNTIF('Trade Log'!M:M,">0")
A10: Losing Trades: | B10: =COUNTIF('Trade Log'!M:M,"<0")
A11: Win Rate: | B11: =COUNTIF('Trade Log'!M:M,">0")/COUNTA('Trade Log'!M:M)
A12: Average Win: | B12: =AVERAGEIF('Trade Log'!M:M,">0")
A13: Average Loss: | B13: =AVERAGEIF('Trade Log'!M:M,"<0")

Sheet Current Positions
A1: Symbol | B1: Shares | C1: Entry Price | D1: Entry Date | E1: Current Price | F1: Current Value | G1: Unrealized P&L | H1: Unrealized %
A3: FDX | B3: 17 | C3: 288.78 | D3: 46013 | E3: 385.95 | F3: 4909.26 | G3: 6561.15 | H3: 1651.89 | I3: 0.33648452
A4: MS | B4: 28 | C4: 176.98 | D4: 46013 | E4: 191.05 | F4: 4955.44 | G4: 5349.4 | H4: 393.96 | I4: 0.079500509
A5: INTC | B5: 138 | C5: 36.37 | D5: 46014 | E5: 65.27 | F5: 5019.06 | G5: 9007.26 | H5: 3988.2 | I5: 0.79461094
A6: LMT | B6: 10 | C6: 497.07 | D6: 46027 | E6: 555.43 | F6: 4970.7 | G6: 5554.3 | H6: 583.6 | I6: 0.11740801
A7: GS | B7: 5 | C7: 914.34 | D7: 46027 | E7: 934.84 | F7: 4571.7 | G7: 4674.2 | H7: 102.5 | I7: 0.022420544
A8: KO | B8: 73 | C8: 69.37 | D8: 46030 | E8: 74.63 | F8: 5064.01 | G8: 5447.99 | H8: 383.98 | I8: 0.075825285
A9: PFE | B9: 199 | C9: 26.5 | D9: 46049 | E9: 26.8 | F9: 5273.5 | G9: 5333.2 | H9: 59.7 | I9: 0.011320755
A10: NOW | B10: 41 | C10: 129.62 | D10: 46051 | E10: 103.07 | F10: 5314.42 | G10: 4225.87 | H10: -1088.55 | I10: -0.2048295
A11: PEP | B11: 34 | C11: 153.63 | D11: 46055 | E11: 153.79 | F11: 5223.42 | G11: 5228.86 | H11: 5.44 | I11: 0.0010414633
A12: C | B12: 44 | C12: 122.15 | D12: 46063 | E12: 129.73 | F12: 5374.6 | G12: 5708.12 | H12: 333.52 | I12: 0.062054851
A13: TMF | B13: 132 | C13: 40.01 | D13: 46076 | E13: 36.28 | F13: 5281.32 | G13: 4788.96 | H13: -492.36 | I13: -0.093226693
A14: GOOGL | B14: 17 | C14: 307.9 | D14: 46098 | E14: 339.32 | F14: 5234.3 | G14: 5768.44 | H14: 534.14 | I14: 0.10204612
... A20: LABU | B20: 32 | C20: 154.9 | D20: 46107 | E20: 204.13 | F20: 4956.8 | G20: 6532.16 | H20: 1575.36 | I20: 0.31781795
